popt/__init__.py
popt/popt.py
popt-0.4.dist-info/LICENSE
popt-0.4.dist-info/METADATA
popt-0.4.dist-info/WHEEL
popt-0.4.dist-info/entry_points.txt
popt-0.4.dist-info/top_level.txt
popt-0.4.dist-info/RECORD
