Metadata-Version: 2.1
Name: popt
Version: 0.4
Summary: Tool for converting Robot Framework xml output to a human-readable log file
Home-page: https://github.com/jkohvakk/popt
Author: Janne Kohvakka
Author-email: jkohvakk@gmail.com
License: UNKNOWN
Keywords: Robot Framework,log
Platform: UNKNOWN
Provides-Extra: test
Requires-Dist: pytest ; extra == 'test'
Requires-Dist: mock ; extra == 'test'
